mdict_query_r/__init__.py
mdict_query_r/db_manager.py
mdict_query_r/index_builder.py
mdict_query_r/mdict.py
mdict_query_r/query.py
mdict_query_r/lib/__init__.py
mdict_query_r/lib/lzo.py
mdict_query_r/lib/pureSalsa20.py
mdict_query_r/lib/readmdict.py
mdict_query_r/lib/ripemd128.py
mdict_query_r/lib/writemdict.py
mdict_query_r-0.3.1.dist-info/METADATA
mdict_query_r-0.3.1.dist-info/WHEEL
mdict_query_r-0.3.1.dist-info/top_level.txt
mdict_query_r-0.3.1.dist-info/RECORD
