Metadata-Version: 2.4
Name: mdict_query_r
Version: 0.3.1
Summary: A package to query mdict
Author-email: aaaaaaMao <bmiemaojie@163.com>
Project-URL: Homepage, https://github.com/aaaaaaMao/mdict-query-r
Project-URL: Issues, https://github.com/aaaaaaMao/mdict-query-r/issues
Classifier: Programming Language :: Python :: 3
Classifier: Operating System :: OS Independent
Requires-Python: >=3.6
Requires-Dist: peewee
Requires-Dist: xxhash
